{
  "slug": "delete-nodes-and-return-forest",
  "link": "https://leetcode.com/problems/delete-nodes-and-return-forest/",
  "difficulty": "Medium",
  "index": "1115",
  "description_full": "Given the root of a binary tree, each node in the tree has a distinct value.\n\nAfter deleting all nodes with a value in to_delete, we are left with a forest (a disjoint union of trees).\n\nReturn the roots of the trees in the remaining forest. You may return the result in any order.\n\n \nExample 1:\n\n\nInput: root = [1,2,3,4,5,6,7], to_delete = [3,5]\nOutput: [[1,2,null,4],[6],[7]]\n\n\nExample 2:\n\n\nInput: root = [1,2,4,null,3], to_delete = [3]\nOutput: [[1,2,4]]\n\n\n \nConstraints:\n\n\n\tThe number of nodes in the given tree is at most 1000.\n\tEach node has a distinct value between 1 and 1000.\n\tto_delete.length <= 1000\n\tto_delete contains distinct values between 1 and 1000.\n\n",
  "description": "Given the root of a binary tree, each node in the tree has a distinct value.\n\nAfter deleting all nodes with a value in to_delete, we are left with a forest (a disjoint union of trees).\n\nReturn the roots of the trees in the remaining forest. You may return the result in any order.",
  "example": "Input: root = [1,2,3,4,5,6,7], to_delete = [3,5]\nOutput: [[1,2,null,4],[6],[7]]",
  "constraints_text": "The number of nodes in the given tree is at most 1000.\n\tEach node has a distinct value between 1 and 1000.\n\tto_delete.length <= 1000\n\tto_delete contains distinct values between 1 and 1000.",
  "templates": {
    "c": "/**\n * Definition for a binary tree node.\n * struct TreeNode {\n *     int val;\n *     struct TreeNode *left;\n *     struct TreeNode *right;\n * };\n */\n\n\n/**\n * Note: The returned array must be malloced, assume caller calls free().\n */\nstruct TreeNode** delNodes(struct TreeNode* root, int* to_delete, int to_deleteSize, int* returnSize){\n\n}",
    "cpp": "/**\n * Definition for a binary tree node.\n * struct TreeNode {\n *     int val;\n *     TreeNode *left;\n *     TreeNode *right;\n *     TreeNode() : val(0), left(nullptr), right(nullptr) {}\n *     TreeNode(int x) : val(x), left(nullptr), right(nullptr) {}\n *     TreeNode(int x, TreeNode *left, TreeNode *right) : val(x), left(left), right(right) {}\n * };\n */\nclass Solution {\npublic:\n    vector<TreeNode*> delNodes(TreeNode* root, vector<int>& to_delete) {\n        \n    }\n};",
    "java": "/**\n * Definition for a binary tree node.\n * public class TreeNode {\n *     int val;\n *     TreeNode left;\n *     TreeNode right;\n *     TreeNode() {}\n *     TreeNode(int val) { this.val = val; }\n *     TreeNode(int val, TreeNode left, TreeNode right) {\n *         this.val = val;\n *         this.left = left;\n *         this.right = right;\n *     }\n * }\n */\nclass Solution {\n    public List<TreeNode> delNodes(TreeNode root, int[] to_delete) {\n        \n    }\n}",
    "javascript": "/**\n * Definition for a binary tree node.\n * function TreeNode(val, left, right) {\n *     this.val = (val===undefined ? 0 : val)\n *     this.left = (left===undefined ? null : left)\n *     this.right = (right===undefined ? null : right)\n * }\n */\n/**\n * @param {TreeNode} root\n * @param {number[]} to_delete\n * @return {TreeNode[]}\n */\nvar delNodes = function(root, to_delete) {\n    \n};",
    "python": "# Definition for a binary tree node.\n# class TreeNode(object):\n#     def __init__(self, val=0, left=None, right=None):\n#         self.val = val\n#         self.left = left\n#         self.right = right\nclass Solution(object):\n    def delNodes(self, root, to_delete):\n        \"\"\"\n        :type root: TreeNode\n        :type to_delete: List[int]\n        :rtype: List[TreeNode]\n        \"\"\"\n        "
  },
  "subtasks": [
    {
      "intent": "Preprocess the list of values to delete into an efficient lookup structure.",
      "structures": [
        "tree"
      ],
      "actions": [
        "hashing"
      ],
      "cues": [
        "to-delete"
      ],
      "constraints": [
        "distinct-values",
        "1-to-1000"
      ]
    },
    {
      "intent": "Recursively traverse the binary tree, prune deleted nodes, and collect roots of remaining subtrees.",
      "structures": [
        "tree",
        "array"
      ],
      "actions": [
        "dfs",
        "recursion"
      ],
      "cues": [
        "root-of-a-binary-tree",
        "deleting-all-nodes",
        "remaining-forest",
        "return-the-roots"
      ],
      "constraints": [
        "distinct-value",
        "at-most-1000-nodes"
      ]
    }
  ]
}